docs/conf.py
jaxparrow/__init__.py
jaxparrow/__main__.py
jaxparrow/cyclogeostrophy.py
jaxparrow/geostrophy.py
jaxparrow/version.py
jaxparrow/tools/__init__.py
jaxparrow/tools/geometry.py
jaxparrow/tools/kinematics.py
jaxparrow/tools/operators.py
jaxparrow/tools/sanitize.py
notebooks/duacs_visualisation.py
tests/gaussian_eddy.py
tests/test_velocities.py
jaxparrow-0.2.2.dist-info/LICENSE
jaxparrow-0.2.2.dist-info/METADATA
jaxparrow-0.2.2.dist-info/WHEEL
jaxparrow-0.2.2.dist-info/entry_points.txt
jaxparrow-0.2.2.dist-info/top_level.txt
jaxparrow-0.2.2.dist-info/RECORD
