Metadata-Version: 2.1
Name: jaxparrow
Version: 0.2.2
Summary: Computes the inversion of the cyclogeostrophic balance based on a variational formulation approach, using JAX
Author-email: Vadim Bertrand <vadim.bertrand@univ-grenoble-alpes.fr>, Victor E V Z De Almeida <victorzaia@outlook.com>, Julien Le Sommer <julien.lesommer@univ-grenoble-alpes.fr>, Emmanuel Cosme <emmanuel.cosme@univ-grenoble-alpes.fr>
License: Apache-2.0
Project-URL: Homepage, https://jaxparrow.readthedocs.io/
Project-URL: Bug Tracker, https://github.com/meom-group/jaxparrow/issues
Keywords: cyclogeostrophy,eddy,flow,geostrophy,jax,swirl,velocity
Classifier: Programming Language :: Python :: 3
Classifier: License :: OSI Approved :: Apache Software License
Classifier: Operating System :: OS Independent
Requires-Python: >=3.9
License-File: LICENSE
Requires-Dist: netCDF4
Requires-Dist: numpy
Requires-Dist: pyyaml
Requires-Dist: tqdm
Requires-Dist: xarray
Requires-Dist: jax
Requires-Dist: jaxlib
Requires-Dist: jaxtyping
Requires-Dist: optax
Provides-Extra: dev
Requires-Dist: pytest ; extra == 'dev'
Requires-Dist: sphinx ; extra == 'dev'
Requires-Dist: myst-parser ; extra == 'dev'
Requires-Dist: twine ; extra == 'dev'
Requires-Dist: build ; extra == 'dev'
Provides-Extra: notebook
Requires-Dist: jupyterlab ; extra == 'notebook'
Requires-Dist: matplotlib ; extra == 'notebook'
